LICENSE.txt
README.txt
setup.py
src/zif/__init__.py
src/zif.sedna.egg-info/PKG-INFO
src/zif.sedna.egg-info/SOURCES.txt
src/zif.sedna.egg-info/dependency_links.txt
src/zif.sedna.egg-info/namespace_packages.txt
src/zif.sedna.egg-info/not-zip-safe
src/zif.sedna.egg-info/requires.txt
src/zif.sedna.egg-info/top_level.txt
src/zif/sedna/README.txt
src/zif/sedna/README_da.txt
src/zif/sedna/README_pylons.txt
src/zif/sedna/README_sednaobject.txt
src/zif/sedna/__init__.py
src/zif/sedna/da.py
src/zif/sedna/dbapi.py
src/zif/sedna/dbapiexceptions.py
src/zif/sedna/dbapitest.py
src/zif/sedna/externals.py
src/zif/sedna/msgcodes.py
src/zif/sedna/pool.py
src/zif/sedna/protocol.py
src/zif/sedna/sednaobject.py
src/zif/sedna/tests.py
src/zif/sedna/example/ot.py
src/zif/sedna/example/region.xml