Metadata-Version: 1.0
Name: zif.sedna
Version: 0.10alpha1
Summary: Sedna XML Database adapter
Home-page: http://zif.svn.sourceforge.net/viewvc/zif/zif.sedna
Author: Jim Washington
Author-email: jwashin@vt.edu
License: BSD
Keywords: sedna xml database zope persistence xquery
Platform: UNKNOWN
